solution_efe_setup/__init__.py
solution_efe_setup/create.py
solution_efe_setup-1.0.0.dist-info/METADATA
solution_efe_setup-1.0.0.dist-info/WHEEL
solution_efe_setup-1.0.0.dist-info/top_level.txt
solution_efe_setup-1.0.0.dist-info/RECORD
