Metadata-Version: 2.1
Name: solution-efe-setup
Version: 1.0.0
Summary: Paquete de preparacion
Home-page: UNKNOWN
Author: Rulman Ferro
Author-email: rulman26@gmail.com
License: MIT
Platform: UNKNOWN
Requires-Python: >=3.6
Requires-Dist: Flask
Requires-Dist: flask-swagger-ui
Requires-Dist: solution-efe-config
